quran_ayah_lookup/__init__.py
quran_ayah_lookup/api.py
quran_ayah_lookup/cli.py
quran_ayah_lookup/loader.py
quran_ayah_lookup/models.py
quran_ayah_lookup/text_utils.py
quran_ayah_lookup/resources/quran-uthmani_all.txt
quran_ayah_lookup/resources/simple-clean.txt
quran_ayah_lookup/resources/simple-minimal.txt
quran_ayah_lookup/resources/simple-plain.txt
quran_ayah_lookup/resources/simple.txt
quran_ayah_lookup/resources/uthmani.txt
quran_ayah_lookup-0.1.5.dist-info/licenses/LICENSE
quran_ayah_lookup-0.1.5.dist-info/METADATA
quran_ayah_lookup-0.1.5.dist-info/WHEEL
quran_ayah_lookup-0.1.5.dist-info/entry_points.txt
quran_ayah_lookup-0.1.5.dist-info/top_level.txt
quran_ayah_lookup-0.1.5.dist-info/RECORD
