Metadata-Version: 2.4
Name: quran-ayah-lookup
Version: 0.1.5
Summary: A Python package for looking up Quranic ayahs by their number or Arabic text. Uses Quran corpus from Tanzil.net. Arabic only, no translations supported.
Author-email: Sayed Mahmoud <foss-support@sayedmahmoud266.website>
Maintainer-email: Sayed Mahmoud <foss-support@sayedmahmoud266.website>
License: MIT
Project-URL: Homepage, https://github.com/sayedmahmoud266/quran-ayah-lookup
Project-URL: Repository, https://github.com/sayedmahmoud266/quran-ayah-lookup
Project-URL: Documentation, https://github.com/sayedmahmoud266/quran-ayah-lookup/blob/main/README.md
Project-URL: Bug Tracker, https://github.com/sayedmahmoud266/quran-ayah-lookup/issues
Keywords: quran,ayah,lookup,islamic,search,text
Classifier: Development Status :: 3 - Alpha
Classifier: Intended Audience :: Developers
Classifier: Intended Audience :: Religion
Classifier: License :: OSI Approved :: MIT License
Classifier: Operating System :: OS Independent
Classifier: Programming Language :: Python :: 3
Classifier: Programming Language :: Python :: 3.8
Classifier: Programming Language :: Python :: 3.9
Classifier: Programming Language :: Python :: 3.10
Classifier: Programming Language :: Python :: 3.11
Classifier: Programming Language :: Python :: 3.12
Classifier: Topic :: Religion
Classifier: Topic :: Text Processing :: Linguistic
Classifier: Topic :: Software Development :: Libraries :: Python Modules
Requires-Python: >=3.8
License-File: LICENSE
Requires-Dist: rapidfuzz>=3.0.0
Requires-Dist: numpy>=2.0.0
Requires-Dist: click>=8.0.0
Requires-Dist: python-dotenv>=1.0.0
Provides-Extra: api
Requires-Dist: fastapi>=0.104.0; extra == "api"
Requires-Dist: uvicorn[standard]>=0.24.0; extra == "api"
Provides-Extra: dev
Requires-Dist: pytest>=7.0; extra == "dev"
Requires-Dist: pytest-cov>=4.0; extra == "dev"
Requires-Dist: pytest-asyncio>=0.21.0; extra == "dev"
Requires-Dist: httpx>=0.25.0; extra == "dev"
Requires-Dist: black>=22.0; extra == "dev"
Requires-Dist: flake8>=5.0; extra == "dev"
Requires-Dist: mypy>=1.0; extra == "dev"
Requires-Dist: build>=0.8; extra == "dev"
Requires-Dist: twine>=4.0; extra == "dev"
Dynamic: license-file
